<root>
<fcs name="fcs_-1008270057#1" edge="-1008270057#1" slots="10" bus="B3_24" x="19116.1" y="17384.1">
  <pbuy>
    <item btime="0" price="1.0" />
  </pbuy>
</fcs>
<fcs name="fcs_-1050551873" edge="-1050551873" slots="10" bus="B3_14" x="16275.8" y="29727.0">
  <pbuy>
    <item btime="0" price="1.0" />
  </pbuy>
</fcs>
<fcs name="fcs_-1184565351" edge="-1184565351" slots="10" bus="B0_18" x="16560.7" y="19379.3">
  <pbuy>
    <item btime="0" price="1.0" />
  </pbuy>
</fcs>
<fcs name="fcs_-122605005#3" edge="-122605005#3" slots="10" bus="B0_12" x="14353.0" y="17649.3">
  <pbuy>
    <item btime="0" price="1.0" />
  </pbuy>
</fcs>
<fcs name="fcs_-122605049#7" edge="-122605049#7" slots="10" bus="B2_24" x="14285.3" y="20058.1">
  <pbuy>
    <item btime="0" price="1.0" />
  </pbuy>
</fcs>
<fcs name="fcs_-190344568#1" edge="-190344568#1" slots="10" bus="B2_23" x="13549.4" y="18450.7">
  <pbuy>
    <item btime="0" price="1.0" />
  </pbuy>
</fcs>
<fcs name="fcs_-190507008#6" edge="-190507008#6" slots="10" bus="B2_6" x="12617.9" y="21799.9">
  <pbuy>
    <item btime="0" price="1.0" />
  </pbuy>
</fcs>
<fcs name="fcs_-190507038#1" edge="-190507038#1" slots="10" bus="B2_7" x="11441.3" y="22092.1">
  <pbuy>
    <item btime="0" price="1.0" />
  </pbuy>
</fcs>
<fcs name="fcs_-198710135#1" edge="-198710135#1" slots="10" bus="B2_28" x="13873.2" y="23898.2">
  <pbuy>
    <item btime="0" price="1.0" />
  </pbuy>
</fcs>
<fcs name="fcs_-297305079#0" edge="-297305079#0" slots="10" bus="B2_27" x="16124.1" y="22262.5">
  <pbuy>
    <item btime="0" price="1.0" />
  </pbuy>
</fcs>
<fcs name="fcs_-297905340#0" edge="-297905340#0" slots="10" bus="B2_28" x="14871.5" y="23231.0">
  <pbuy>
    <item btime="0" price="1.0" />
  </pbuy>
</fcs>
<fcs name="fcs_-328760678#6" edge="-328760678#6" slots="10" bus="B2_22" x="15865.6" y="17423.2">
  <pbuy>
    <item btime="0" price="1.0" />
  </pbuy>
</fcs>
<fcs name="fcs_-328760680#2" edge="-328760680#2" slots="10" bus="B3_25" x="16649.4" y="17432.8">
  <pbuy>
    <item btime="0" price="1.0" />
  </pbuy>
</fcs>
<fcs name="fcs_-353238481#6" edge="-353238481#6" slots="10" bus="B3_30" x="22938.0" y="22584.3">
  <pbuy>
    <item btime="0" price="1.0" />
  </pbuy>
</fcs>
<fcs name="fcs_-353238487" edge="-353238487" slots="10" bus="B3_28" x="22762.5" y="27276.2">
  <pbuy>
    <item btime="0" price="1.0" />
  </pbuy>
</fcs>
<fcs name="fcs_-353238497#4" edge="-353238497#4" slots="10" bus="B0_17" x="18374.5" y="19366.0">
  <pbuy>
    <item btime="0" price="1.0" />
  </pbuy>
</fcs>
<fcs name="fcs_-353238497#9" edge="-353238497#9" slots="10" bus="B0_16" x="19072.7" y="18365.1">
  <pbuy>
    <item btime="0" price="1.0" />
  </pbuy>
</fcs>
<fcs name="fcs_-416935569#3" edge="-416935569#3" slots="10" bus="B2_30" x="12287.3" y="26622.4">
  <pbuy>
    <item btime="0" price="1.0" />
  </pbuy>
</fcs>
<fcs name="fcs_-427319938#3" edge="-427319938#3" slots="10" bus="B3_5" x="22594.5" y="20429.1">
  <pbuy>
    <item btime="0" price="1.0" />
  </pbuy>
</fcs>
<fcs name="fcs_-429010271#5" edge="-429010271#5" slots="10" bus="B3_4" x="24015.4" y="18960.2">
  <pbuy>
    <item btime="0" price="1.0" />
  </pbuy>
</fcs>
<fcs name="fcs_-431490036#10" edge="-431490036#10" slots="10" bus="B3_25" x="17302.4" y="16189.6">
  <pbuy>
    <item btime="0" price="1.0" />
  </pbuy>
</fcs>
<fcs name="fcs_-431599637#12" edge="-431599637#12" slots="10" bus="B2_6" x="11753.1" y="19488.6">
  <pbuy>
    <item btime="0" price="1.0" />
  </pbuy>
</fcs>
<fcs name="fcs_-463119314#3" edge="-463119314#3" slots="10" bus="B2_28" x="14435.2" y="22612.9">
  <pbuy>
    <item btime="0" price="1.0" />
  </pbuy>
</fcs>
<fcs name="fcs_-463638341#0" edge="-463638341#0" slots="10" bus="B2_22" x="15735.8" y="19904.7">
  <pbuy>
    <item btime="0" price="1.0" />
  </pbuy>
</fcs>
<fcs name="fcs_-463638341#1" edge="-463638341#1" slots="10" bus="B0_18" x="16622.4" y="19079.7">
  <pbuy>
    <item btime="0" price="1.0" />
  </pbuy>
</fcs>
<fcs name="fcs_-464078883#1" edge="-464078883#1" slots="10" bus="B2_30" x="13063.3" y="26896.1">
  <pbuy>
    <item btime="0" price="1.0" />
  </pbuy>
</fcs>
<fcs name="fcs_-465145598#2" edge="-465145598#2" slots="10" bus="B2_28" x="12665.6" y="23537.5">
  <pbuy>
    <item btime="0" price="1.0" />
  </pbuy>
</fcs>
<fcs name="fcs_-465876790#0" edge="-465876790#0" slots="10" bus="B3_9" x="17740.7" y="24158.8">
  <pbuy>
    <item btime="0" price="1.0" />
  </pbuy>
</fcs>
<fcs name="fcs_-539225492#0" edge="-539225492#0" slots="10" bus="B2_24" x="15618.9" y="18833.2">
  <pbuy>
    <item btime="0" price="1.0" />
  </pbuy>
</fcs>
<fcs name="fcs_-539226214#4" edge="-539226214#4" slots="10" bus="B2_26" x="13814.9" y="22107.7">
  <pbuy>
    <item btime="0" price="1.0" />
  </pbuy>
</fcs>
<fcs name="fcs_-639970236#1" edge="-639970236#1" slots="10" bus="B3_11" x="16570.9" y="26072.4">
  <pbuy>
    <item btime="0" price="1.0" />
  </pbuy>
</fcs>
<fcs name="fcs_-652196712#1" edge="-652196712#1" slots="10" bus="B2_22" x="15985.1" y="17894.3">
  <pbuy>
    <item btime="0" price="1.0" />
  </pbuy>
</fcs>
<fcs name="fcs_-82251575#3" edge="-82251575#3" slots="10" bus="B0_18" x="17322.3" y="19347.9">
  <pbuy>
    <item btime="0" price="1.0" />
  </pbuy>
</fcs>
<fcs name="fcs_-972905121#0" edge="-972905121#0" slots="10" bus="B3_25" x="17368.1" y="18407.5">
  <pbuy>
    <item btime="0" price="1.0" />
  </pbuy>
</fcs>
<fcs name="fcs_-972905121#2" edge="-972905121#2" slots="10" bus="B0_18" x="17731.8" y="18695.8">
  <pbuy>
    <item btime="0" price="1.0" />
  </pbuy>
</fcs>
<fcs name="fcs_1007980698#12" edge="1007980698#12" slots="10" bus="B2_7" x="12226.1" y="22188.1">
  <pbuy>
    <item btime="0" price="1.0" />
  </pbuy>
</fcs>
<fcs name="fcs_1008270058#8" edge="1008270058#8" slots="10" bus="B0_17" x="17823.9" y="19318.8">
  <pbuy>
    <item btime="0" price="1.0" />
  </pbuy>
</fcs>
<fcs name="fcs_1113574525#2" edge="1113574525#2" slots="10" bus="B3_8" x="17943.3" y="23399.7">
  <pbuy>
    <item btime="0" price="1.0" />
  </pbuy>
</fcs>
<fcs name="fcs_1184565320#0-AddedOffRampEdge" edge="1184565320#0-AddedOffRampEdge" slots="10" bus="B2_25" x="17083.3" y="21688.0">
  <pbuy>
    <item btime="0" price="1.0" />
  </pbuy>
</fcs>
<fcs name="fcs_1184565343#1" edge="1184565343#1" slots="10" bus="B2_25" x="16521.3" y="20053.1">
  <pbuy>
    <item btime="0" price="1.0" />
  </pbuy>
</fcs>
<fcs name="fcs_1184565865#1" edge="1184565865#1" slots="10" bus="B3_28" x="20228.8" y="27523.9">
  <pbuy>
    <item btime="0" price="1.0" />
  </pbuy>
</fcs>
<fcs name="fcs_122605005#3" edge="122605005#3" slots="10" bus="B0_12" x="14535.0" y="17869.4">
  <pbuy>
    <item btime="0" price="1.0" />
  </pbuy>
</fcs>
<fcs name="fcs_122605005#6" edge="122605005#6" slots="10" bus="B2_21" x="13749.6" y="17274.5">
  <pbuy>
    <item btime="0" price="1.0" />
  </pbuy>
</fcs>
<fcs name="fcs_122605014#15" edge="122605014#15" slots="10" bus="B2_22" x="16937.8" y="18239.7">
  <pbuy>
    <item btime="0" price="1.0" />
  </pbuy>
</fcs>
<fcs name="fcs_122605014#20" edge="122605014#20" slots="10" bus="B2_22" x="16321.7" y="19064.0">
  <pbuy>
    <item btime="0" price="1.0" />
  </pbuy>
</fcs>
<fcs name="fcs_122605049#5" edge="122605049#5" slots="10" bus="B2_26" x="13938.7" y="20717.0">
  <pbuy>
    <item btime="0" price="1.0" />
  </pbuy>
</fcs>
<fcs name="fcs_1288410228" edge="1288410228" slots="10" bus="B2_27" x="16818.4" y="22092.5">
  <pbuy>
    <item btime="0" price="1.0" />
  </pbuy>
</fcs>
<fcs name="fcs_1295372236" edge="1295372236" slots="10" bus="B3_24" x="19168.0" y="18572.2">
  <pbuy>
    <item btime="0" price="1.0" />
  </pbuy>
</fcs>
<fcs name="fcs_190344533#38" edge="190344533#38" slots="10" bus="B3_25" x="16388.6" y="16869.3">
  <pbuy>
    <item btime="0" price="1.0" />
  </pbuy>
</fcs>
<fcs name="fcs_190344568#7" edge="190344568#7" slots="10" bus="B2_24" x="14726.2" y="19175.6">
  <pbuy>
    <item btime="0" price="1.0" />
  </pbuy>
</fcs>
<fcs name="fcs_190507026#5" edge="190507026#5" slots="10" bus="B3_8" x="19106.8" y="23192.4">
  <pbuy>
    <item btime="0" price="1.0" />
  </pbuy>
</fcs>
<fcs name="fcs_190507037#4" edge="190507037#4" slots="10" bus="B2_27" x="15812.0" y="21582.0">
  <pbuy>
    <item btime="0" price="1.0" />
  </pbuy>
</fcs>
<fcs name="fcs_190507108#1" edge="190507108#1" slots="10" bus="B2_26" x="14558.9" y="20874.1">
  <pbuy>
    <item btime="0" price="1.0" />
  </pbuy>
</fcs>
<fcs name="fcs_190507111#1" edge="190507111#1" slots="10" bus="B2_28" x="15142.8" y="22987.6">
  <pbuy>
    <item btime="0" price="1.0" />
  </pbuy>
</fcs>
<fcs name="fcs_190507148#3" edge="190507148#3" slots="10" bus="B2_25" x="17204.4" y="20615.7">
  <pbuy>
    <item btime="0" price="1.0" />
  </pbuy>
</fcs>
<fcs name="fcs_190507183#2" edge="190507183#2" slots="10" bus="B2_27" x="16195.9" y="23096.7">
  <pbuy>
    <item btime="0" price="1.0" />
  </pbuy>
</fcs>
<fcs name="fcs_334168336#13" edge="334168336#13" slots="10" bus="B0_17" x="18763.2" y="19174.2">
  <pbuy>
    <item btime="0" price="1.0" />
  </pbuy>
</fcs>
<fcs name="fcs_334168356#14" edge="334168356#14" slots="10" bus="B2_27" x="15001.4" y="21546.8">
  <pbuy>
    <item btime="0" price="1.0" />
  </pbuy>
</fcs>
<fcs name="fcs_334168358#4" edge="334168358#4" slots="10" bus="B0_16" x="19503.0" y="18535.1">
  <pbuy>
    <item btime="0" price="1.0" />
  </pbuy>
</fcs>
<fcs name="fcs_353238481#6" edge="353238481#6" slots="10" bus="B3_30" x="22983.0" y="22540.4">
  <pbuy>
    <item btime="0" price="1.0" />
  </pbuy>
</fcs>
<fcs name="fcs_353238497#1" edge="353238497#1" slots="10" bus="B0_17" x="17669.7" y="20269.5">
  <pbuy>
    <item btime="0" price="1.0" />
  </pbuy>
</fcs>
<fcs name="fcs_353238497#9" edge="353238497#9" slots="10" bus="B0_16" x="18874.2" y="18016.6">
  <pbuy>
    <item btime="0" price="1.0" />
  </pbuy>
</fcs>
<fcs name="fcs_416896039#13" edge="416896039#13" slots="10" bus="B3_8" x="19069.6" y="23130.8">
  <pbuy>
    <item btime="0" price="1.0" />
  </pbuy>
</fcs>
<fcs name="fcs_416896039#15" edge="416896039#15" slots="10" bus="B3_8" x="19170.3" y="22922.7">
  <pbuy>
    <item btime="0" price="1.0" />
  </pbuy>
</fcs>
<fcs name="fcs_416896076#13" edge="416896076#13" slots="10" bus="B2_21" x="14036.1" y="16949.3">
  <pbuy>
    <item btime="0" price="1.0" />
  </pbuy>
</fcs>
<fcs name="fcs_416902874#3" edge="416902874#3" slots="10" bus="B2_28" x="15472.4" y="24618.2">
  <pbuy>
    <item btime="0" price="1.0" />
  </pbuy>
</fcs>
<fcs name="fcs_416903030#1" edge="416903030#1" slots="10" bus="B3_9" x="16088.1" y="23057.2">
  <pbuy>
    <item btime="0" price="1.0" />
  </pbuy>
</fcs>
<fcs name="fcs_416929754#17" edge="416929754#17" slots="10" bus="B2_21" x="14337.0" y="16892.5">
  <pbuy>
    <item btime="0" price="1.0" />
  </pbuy>
</fcs>
<fcs name="fcs_416929754#29" edge="416929754#29" slots="10" bus="B2_6" x="12826.6" y="19142.2">
  <pbuy>
    <item btime="0" price="1.0" />
  </pbuy>
</fcs>
<fcs name="fcs_416929825#1" edge="416929825#1" slots="10" bus="B3_4" x="22961.4" y="18476.8">
  <pbuy>
    <item btime="0" price="1.0" />
  </pbuy>
</fcs>
<fcs name="fcs_416929825#11" edge="416929825#11" slots="10" bus="B3_6" x="21207.1" y="20953.7">
  <pbuy>
    <item btime="0" price="1.0" />
  </pbuy>
</fcs>
<fcs name="fcs_416929873#4" edge="416929873#4" slots="10" bus="B3_27" x="18321.0" y="25662.6">
  <pbuy>
    <item btime="0" price="1.0" />
  </pbuy>
</fcs>
<fcs name="fcs_416935552#12" edge="416935552#12" slots="10" bus="B3_25" x="17621.7" y="16777.7">
  <pbuy>
    <item btime="0" price="1.0" />
  </pbuy>
</fcs>
<fcs name="fcs_416935552#14" edge="416935552#14" slots="10" bus="B3_25" x="17645.4" y="16074.4">
  <pbuy>
    <item btime="0" price="1.0" />
  </pbuy>
</fcs>
<fcs name="fcs_427189024#1" edge="427189024#1" slots="10" bus="B3_6" x="22392.6" y="22197.6">
  <pbuy>
    <item btime="0" price="1.0" />
  </pbuy>
</fcs>
<fcs name="fcs_427189024#6" edge="427189024#6" slots="10" bus="B3_6" x="21636.2" y="21493.4">
  <pbuy>
    <item btime="0" price="1.0" />
  </pbuy>
</fcs>
<fcs name="fcs_427189025#2" edge="427189025#2" slots="10" bus="B3_32" x="23909.2" y="19804.3">
  <pbuy>
    <item btime="0" price="1.0" />
  </pbuy>
</fcs>
<fcs name="fcs_427319949#15" edge="427319949#15" slots="10" bus="B3_5" x="23479.3" y="20408.3">
  <pbuy>
    <item btime="0" price="1.0" />
  </pbuy>
</fcs>
<fcs name="fcs_429010271#10" edge="429010271#10" slots="10" bus="B3_4" x="22992.0" y="18329.2">
  <pbuy>
    <item btime="0" price="1.0" />
  </pbuy>
</fcs>
<fcs name="fcs_431488045#2" edge="431488045#2" slots="10" bus="B0_14" x="17793.5" y="15837.2">
  <pbuy>
    <item btime="0" price="1.0" />
  </pbuy>
</fcs>
<fcs name="fcs_431488045#4" edge="431488045#4" slots="10" bus="B0_15" x="18219.8" y="16120.1">
  <pbuy>
    <item btime="0" price="1.0" />
  </pbuy>
</fcs>
<fcs name="fcs_431488046#6" edge="431488046#6" slots="10" bus="B0_14" x="17612.9" y="15900.1">
  <pbuy>
    <item btime="0" price="1.0" />
  </pbuy>
</fcs>
<fcs name="fcs_431490036#14" edge="431490036#14" slots="10" bus="B3_25" x="16426.2" y="17439.6">
  <pbuy>
    <item btime="0" price="1.0" />
  </pbuy>
</fcs>
<fcs name="fcs_463124042#4" edge="463124042#4" slots="10" bus="B3_9" x="16167.0" y="23688.5">
  <pbuy>
    <item btime="0" price="1.0" />
  </pbuy>
</fcs>
<fcs name="fcs_463638341#2" edge="463638341#2" slots="10" bus="B3_25" x="17561.8" y="17560.1">
  <pbuy>
    <item btime="0" price="1.0" />
  </pbuy>
</fcs>
<fcs name="fcs_463638358" edge="463638358" slots="10" bus="B2_28" x="15374.3" y="24551.4">
  <pbuy>
    <item btime="0" price="1.0" />
  </pbuy>
</fcs>
<fcs name="fcs_464011119#0" edge="464011119#0" slots="10" bus="B2_31" x="14272.2" y="27697.9">
  <pbuy>
    <item btime="0" price="1.0" />
  </pbuy>
</fcs>
<fcs name="fcs_464465899" edge="464465899" slots="10" bus="B2_6" x="12798.8" y="19224.1">
  <pbuy>
    <item btime="0" price="1.0" />
  </pbuy>
</fcs>
<fcs name="fcs_464465899-AddedOffRampEdge" edge="464465899-AddedOffRampEdge" slots="10" bus="B2_6" x="12721.6" y="19374.6">
  <pbuy>
    <item btime="0" price="1.0" />
  </pbuy>
</fcs>
<fcs name="fcs_465145593#1" edge="465145593#1" slots="10" bus="B2_6" x="12840.9" y="20719.4">
  <pbuy>
    <item btime="0" price="1.0" />
  </pbuy>
</fcs>
<fcs name="fcs_468686651#1" edge="468686651#1" slots="10" bus="B3_7" x="19557.3" y="20596.7">
  <pbuy>
    <item btime="0" price="1.0" />
  </pbuy>
</fcs>
<fcs name="fcs_468686660#0" edge="468686660#0" slots="10" bus="B3_6" x="21128.2" y="22076.1">
  <pbuy>
    <item btime="0" price="1.0" />
  </pbuy>
</fcs>
<fcs name="fcs_468686661#6" edge="468686661#6" slots="10" bus="B3_6" x="21755.8" y="22949.9">
  <pbuy>
    <item btime="0" price="1.0" />
  </pbuy>
</fcs>
<fcs name="fcs_468686891#5" edge="468686891#5" slots="10" bus="B2_24" x="14487.4" y="18746.5">
  <pbuy>
    <item btime="0" price="1.0" />
  </pbuy>
</fcs>
<fcs name="fcs_468686892#11" edge="468686892#11" slots="10" bus="B3_25" x="16395.4" y="16508.8">
  <pbuy>
    <item btime="0" price="1.0" />
  </pbuy>
</fcs>
<fcs name="fcs_538751592#1" edge="538751592#1" slots="10" bus="B3_8" x="18830.2" y="22860.7">
  <pbuy>
    <item btime="0" price="1.0" />
  </pbuy>
</fcs>
<fcs name="fcs_538751592#8" edge="538751592#8" slots="10" bus="B3_8" x="19314.2" y="23510.7">
  <pbuy>
    <item btime="0" price="1.0" />
  </pbuy>
</fcs>
<fcs name="fcs_538751601#2" edge="538751601#2" slots="10" bus="B3_27" x="18488.9" y="24777.1">
  <pbuy>
    <item btime="0" price="1.0" />
  </pbuy>
</fcs>
<fcs name="fcs_538788607" edge="538788607" slots="10" bus="B3_5" x="22488.4" y="20690.0">
  <pbuy>
    <item btime="0" price="1.0" />
  </pbuy>
</fcs>
<fcs name="fcs_539225479#1" edge="539225479#1" slots="10" bus="B0_12" x="15619.5" y="18515.3">
  <pbuy>
    <item btime="0" price="1.0" />
  </pbuy>
</fcs>
<fcs name="fcs_539225481#0" edge="539225481#0" slots="10" bus="B2_24" x="15369.7" y="18882.9">
  <pbuy>
    <item btime="0" price="1.0" />
  </pbuy>
</fcs>
<fcs name="fcs_539225488" edge="539225488" slots="10" bus="B0_12" x="15292.9" y="18515.8">
  <pbuy>
    <item btime="0" price="1.0" />
  </pbuy>
</fcs>
<fcs name="fcs_539226214#0" edge="539226214#0" slots="10" bus="B2_7" x="12290.7" y="22275.2">
  <pbuy>
    <item btime="0" price="1.0" />
  </pbuy>
</fcs>
<fcs name="fcs_539226214#4" edge="539226214#4" slots="10" bus="B2_26" x="13815.7" y="22115.7">
  <pbuy>
    <item btime="0" price="1.0" />
  </pbuy>
</fcs>
<fcs name="fcs_539240851#1" edge="539240851#1" slots="10" bus="B2_7" x="11631.8" y="22824.2">
  <pbuy>
    <item btime="0" price="1.0" />
  </pbuy>
</fcs>
<fcs name="fcs_548563010" edge="548563010" slots="10" bus="B3_7" x="19053.4" y="20071.5">
  <pbuy>
    <item btime="0" price="1.0" />
  </pbuy>
</fcs>
<fcs name="fcs_548563038#11" edge="548563038#11" slots="10" bus="B3_32" x="24051.3" y="20155.1">
  <pbuy>
    <item btime="0" price="1.0" />
  </pbuy>
</fcs>
<fcs name="fcs_548563038#8" edge="548563038#8" slots="10" bus="B3_4" x="22910.3" y="19403.1">
  <pbuy>
    <item btime="0" price="1.0" />
  </pbuy>
</fcs>
<fcs name="fcs_548563041#6" edge="548563041#6" slots="10" bus="B3_6" x="21125.5" y="21414.6">
  <pbuy>
    <item btime="0" price="1.0" />
  </pbuy>
</fcs>
<fcs name="fcs_548563043#4" edge="548563043#4" slots="10" bus="B3_6" x="20961.4" y="22316.1">
  <pbuy>
    <item btime="0" price="1.0" />
  </pbuy>
</fcs>
<fcs name="fcs_548563045#10" edge="548563045#10" slots="10" bus="B3_6" x="21512.7" y="21272.3">
  <pbuy>
    <item btime="0" price="1.0" />
  </pbuy>
</fcs>
<fcs name="fcs_548563045#5" edge="548563045#5" slots="10" bus="B3_5" x="22046.4" y="20312.8">
  <pbuy>
    <item btime="0" price="1.0" />
  </pbuy>
</fcs>
<fcs name="fcs_548563062#2" edge="548563062#2" slots="10" bus="B3_8" x="17440.0" y="22827.7">
  <pbuy>
    <item btime="0" price="1.0" />
  </pbuy>
</fcs>
<fcs name="fcs_61575546#7" edge="61575546#7" slots="10" bus="B2_24" x="15139.8" y="18749.9">
  <pbuy>
    <item btime="0" price="1.0" />
  </pbuy>
</fcs>
<fcs name="fcs_652196712#1" edge="652196712#1" slots="10" bus="B2_22" x="15997.0" y="17733.6">
  <pbuy>
    <item btime="0" price="1.0" />
  </pbuy>
</fcs>
<fcs name="fcs_758084004#0" edge="758084004#0" slots="10" bus="B2_30" x="13268.4" y="26494.7">
  <pbuy>
    <item btime="0" price="1.0" />
  </pbuy>
</fcs>
<fcs name="fcs_758110209" edge="758110209" slots="10" bus="B0_16" x="20020.2" y="17091.6">
  <pbuy>
    <item btime="0" price="1.0" />
  </pbuy>
</fcs>
<fcs name="fcs_758110218#11" edge="758110218#11" slots="10" bus="B2_25" x="16958.3" y="20710.8">
  <pbuy>
    <item btime="0" price="1.0" />
  </pbuy>
</fcs>
<fcs name="fcs_758110218#6" edge="758110218#6" slots="10" bus="B0_17" x="17609.8" y="20081.2">
  <pbuy>
    <item btime="0" price="1.0" />
  </pbuy>
</fcs>
<fcs name="fcs_758110245#1-AddedOffRampEdge" edge="758110245#1-AddedOffRampEdge" slots="10" bus="B2_27" x="15857.3" y="21455.4">
  <pbuy>
    <item btime="0" price="1.0" />
  </pbuy>
</fcs>
<fcs name="fcs_758114145#1" edge="758114145#1" slots="10" bus="B2_27" x="16445.6" y="21954.7">
  <pbuy>
    <item btime="0" price="1.0" />
  </pbuy>
</fcs>
<fcs name="fcs_758114152#1" edge="758114152#1" slots="10" bus="B2_6" x="12739.6" y="19605.0">
  <pbuy>
    <item btime="0" price="1.0" />
  </pbuy>
</fcs>
<fcs name="fcs_758115506#22" edge="758115506#22" slots="10" bus="B2_21" x="14383.7" y="16926.3">
  <pbuy>
    <item btime="0" price="1.0" />
  </pbuy>
</fcs>
<fcs name="fcs_82251573#10" edge="82251573#10" slots="10" bus="B3_25" x="17541.7" y="16750.6">
  <pbuy>
    <item btime="0" price="1.0" />
  </pbuy>
</fcs>
<fcs name="fcs_82251573#14" edge="82251573#14" slots="10" bus="B2_22" x="16226.0" y="18051.1">
  <pbuy>
    <item btime="0" price="1.0" />
  </pbuy>
</fcs>
<fcs name="fcs_82251575#3" edge="82251575#3" slots="10" bus="B0_18" x="17519.9" y="19543.7">
  <pbuy>
    <item btime="0" price="1.0" />
  </pbuy>
</fcs>
<fcs name="fcs_829242096#9" edge="829242096#9" slots="10" bus="B2_26" x="13369.2" y="22511.1">
  <pbuy>
    <item btime="0" price="1.0" />
  </pbuy>
</fcs>
<fcs name="fcs_836318187#1" edge="836318187#1" slots="10" bus="B2_29" x="13555.4" y="24619.5">
  <pbuy>
    <item btime="0" price="1.0" />
  </pbuy>
</fcs>
<fcs name="fcs_85428397#11" edge="85428397#11" slots="10" bus="B2_27" x="15279.7" y="21683.6">
  <pbuy>
    <item btime="0" price="1.0" />
  </pbuy>
</fcs>
<fcs name="fcs_967781250" edge="967781250" slots="10" bus="B3_6" x="21640.8" y="21553.2">
  <pbuy>
    <item btime="0" price="1.0" />
  </pbuy>
</fcs>
<fcs name="fcs_967786564" edge="967786564" slots="10" bus="B3_8" x="19310.0" y="23512.2">
  <pbuy>
    <item btime="0" price="1.0" />
  </pbuy>
</fcs>
<fcs name="fcs_967789202#11" edge="967789202#11" slots="10" bus="B2_25" x="18008.6" y="21203.3">
  <pbuy>
    <item btime="0" price="1.0" />
  </pbuy>
</fcs>
<fcs name="fcs_967789203#3" edge="967789203#3" slots="10" bus="B2_25" x="16940.6" y="21824.2">
  <pbuy>
    <item btime="0" price="1.0" />
  </pbuy>
</fcs>
<fcs name="fcs_967793060#1-AddedOffRampEdge" edge="967793060#1-AddedOffRampEdge" slots="10" bus="B2_25" x="17708.2" y="21127.8">
  <pbuy>
    <item btime="0" price="1.0" />
  </pbuy>
</fcs>
<fcs name="fcs_967796724#1" edge="967796724#1" slots="10" bus="B3_26" x="20161.3" y="23819.4">
  <pbuy>
    <item btime="0" price="1.0" />
  </pbuy>
</fcs>
<fcs name="fcs_967796724#2" edge="967796724#2" slots="10" bus="B3_26" x="20211.5" y="23596.8">
  <pbuy>
    <item btime="0" price="1.0" />
  </pbuy>
</fcs>
<fcs name="fcs_967802098" edge="967802098" slots="10" bus="B2_28" x="14464.8" y="24373.1">
  <pbuy>
    <item btime="0" price="1.0" />
  </pbuy>
</fcs>
<fcs name="fcs_967900158" edge="967900158" slots="10" bus="B2_25" x="17187.7" y="21603.2">
  <pbuy>
    <item btime="0" price="1.0" />
  </pbuy>
</fcs>
<fcs name="fcs_972905123#1" edge="972905123#1" slots="10" bus="B0_15" x="19122.5" y="16706.3">
  <pbuy>
    <item btime="0" price="1.0" />
  </pbuy>
</fcs>
<fcs name="fcs_986094436" edge="986094436" slots="10" bus="B2_30" x="12375.6" y="27345.5">
  <pbuy>
    <item btime="0" price="1.0" />
  </pbuy>
</fcs>
<fcs name="fcs_986136556#0" edge="986136556#0" slots="10" bus="B3_5" x="22319.9" y="20309.0">
  <pbuy>
    <item btime="0" price="1.0" />
  </pbuy>
</fcs>
<fcs name="fcs_986136557#7" edge="986136557#7" slots="10" bus="B3_23" x="20284.9" y="19522.3">
  <pbuy>
    <item btime="0" price="1.0" />
  </pbuy>
</fcs>
<fcs name="fcs_986146305#0" edge="986146305#0" slots="10" bus="B2_26" x="14079.4" y="20040.1">
  <pbuy>
    <item btime="0" price="1.0" />
  </pbuy>
</fcs>
<fcs name="fcs_986226284#7" edge="986226284#7" slots="10" bus="B2_24" x="13886.8" y="19217.8">
  <pbuy>
    <item btime="0" price="1.0" />
  </pbuy>
</fcs>
<fcs name="fcs_986226289#4" edge="986226289#4" slots="10" bus="B2_25" x="16199.4" y="20558.6">
  <pbuy>
    <item btime="0" price="1.0" />
  </pbuy>
</fcs>
<fcs name="fcs_986311497#2" edge="986311497#2" slots="10" bus="B0_12" x="15708.6" y="16801.1">
  <pbuy>
    <item btime="0" price="1.0" />
  </pbuy>
</fcs>
</root>