<?xml version='1.0' encoding='utf8'?>
<root><fcs name="fcs_CS1" bind="CS1" slots="10" bus="b0_4" allow_queuing="True" x="9972.0" y="19457.0"><pbuy value="1.0" type="const" /></fcs><fcs name="fcs_CS2" bind="CS2" slots="10" bus="b0_2" allow_queuing="True" x="3572.0" y="16502.0"><pbuy value="1.0" type="const" /></fcs><fcs name="fcs_CS3" bind="CS3" slots="10" bus="b0_8" allow_queuing="True" x="17046.0" y="18820.0"><pbuy value="1.0" type="const" /></fcs><fcs name="fcs_CS4" bind="CS4" slots="10" bus="b0_9" allow_queuing="True" x="15787.0" y="14938.0"><pbuy value="1.0" type="const" /></fcs><fcs name="fcs_CS5" bind="CS5" slots="10" bus="b1_13" allow_queuing="True" x="18213.0" y="12510.0"><pbuy value="1.0" type="const" /></fcs><fcs name="fcs_CS6" bind="CS6" slots="10" bus="b0_11" allow_queuing="True" x="22111.0" y="16561.0"><pbuy value="1.0" type="const" /></fcs><fcs name="fcs_CS7" bind="CS7" slots="10" bus="b1_24" allow_queuing="True" x="12957.0" y="6718.0"><pbuy value="1.0" type="const" /></fcs><fcs name="fcs_CS8" bind="CS8" slots="10" bus="b1_2" allow_queuing="True" x="20190.0" y="4755.0"><pbuy value="1.0" type="const" /></fcs><fcs name="fcs_CS9" bind="CS9" slots="10" bus="b1_8" allow_queuing="True" x="30983.0" y="15487.0"><pbuy value="1.0" type="const" /></fcs><fcs name="fcs_CS10" bind="CS10" slots="10" bus="b1_9" allow_queuing="True" x="29283.0" y="18641.0"><pbuy value="1.0" type="const" /></fcs></root>