<grid Sb="1.0MVA" Ub="10.0kV"><bus ID="B1" Lat="31.927411083440184" Lon="118.6279926605053"><Pd /><Qd /></bus><bus ID="B2" Lat="31.964308126337226" Lon="118.65262276289118"><Pd /><Qd /></bus><bus ID="B3" Lat="31.99529252198409" Lon="118.68792891993986"><Pd /><Qd /></bus><bus ID="B4" Lat="32.02696428512854" Lon="118.72402963206481"><Pd /><Qd /></bus><bus ID="B5" Lat="32.015920587165255" Lon="118.75156752336224"><Pd /><Qd /></bus><bus ID="B6" Lat="32.03277391169122" Lon="118.78336051368944"><Pd /><Qd /></bus><bus ID="B7" Lat="32.043784536070966" Lon="118.81989167460073"><Pd /><Qd /></bus><bus ID="B8" Lat="32.08255453294008" Lon="118.82096757861991"><Pd /><Qd /></bus><bus ID="B9" Lat="32.096150443033395" Lon="118.87695859045124"><Pd /><Qd /></bus><bus ID="B10" Lat="32.12674928919784" Lon="118.86341911202223"><Pd /><Qd /></bus><bus ID="B11" Lat="32.169666990570185" Lon="118.83163406269793"><Pd /><Qd /></bus><bus ID="B12" Lat="32.17840580941215" Lon="118.78867055206801"><Pd /><Qd /></bus><bus ID="B13" Lat="32.15287150105318" Lon="118.72910702123885"><Pd /><Qd /></bus><bus ID="B14" Lat="32.163663218803194" Lon="118.65898517721507"><Pd /><Qd /></bus><bus ID="B15" Lat="32.11611931309308" Lon="118.687070047503"><Pd /><Qd /></bus><bus ID="B16" Lat="32.10444919776699" Lon="118.65791345876698"><Pd /><Qd /></bus><bus ID="B17" Lat="32.091414939587125" Lon="118.62432628901345"><Pd /><Qd /></bus><bus ID="B18" Lat="32.054252204518455" Lon="118.62231522137138"><Pd /><Qd /></bus><bus ID="B19" Lat="32.00036726528878" Lon="118.59768421509666"><Pd /><Qd /></bus><bus ID="B20" Lat="32.04075622253355" Lon="118.57232453994035"><Pd /><Qd /></bus><bus ID="B21" Lat="32.09619193087123" Lon="118.56548444439802"><Pd /><Qd /></bus><bus ID="B22" Lat="32.125273974614906" Lon="118.59138836775567"><Pd /><Qd /></bus><bus ID="B23" Lat="32.04996325960963" Lon="118.6858742459605"><Pd /><Qd /></bus><bus ID="B24" Lat="32.07168788486608" Lon="118.7421349350582"><Pd /><Qd /></bus><bus ID="B25" Lat="32.09731637124258" Lon="118.7649722081766"><Pd /><Qd /></bus><bus ID="B26" Lat="32.00388751665937" Lon="118.83398581284543"><Pd /><Qd /></bus><bus ID="B27" Lat="31.96899054922042" Lon="118.7904379511723"><Pd /><Qd /></bus><bus ID="B28" Lat="31.972277991599032" Lon="118.74254057288391"><Pd /><Qd /></bus><bus ID="B29" Lat="31.932903966537022" Lon="118.78482097518902"><Pd /><Qd /></bus><bus ID="B30" Lat="31.95404312949352" Lon="118.86391864300809"><Pd /><Qd /></bus><bus ID="B31" Lat="31.982052265518522" Lon="118.90138094708328"><Pd /><Qd /></bus><bus ID="B32" Lat="32.06245733395088" Lon="118.90861085267717"><Pd /><Qd /></bus><bus ID="B33" Lat="32.12505151164465" Lon="118.9437869300573"><Pd /><Qd /></bus><line ID="L1" From="B1" To="B2" R="0.0009220000000000001" X="0.00047" /><line ID="L2" From="B2" To="B3" R="0.00493" X="0.0025109999999999998" /><line ID="L3" From="B3" To="B4" R="0.00366" X="0.0018640000000000002" /><line ID="L4" From="B4" To="B5" R="0.003811" X="0.001941" /><line ID="L5" From="B5" To="B6" R="0.00819" X="0.00707" /><line ID="L6" From="B6" To="B7" R="0.001872" X="0.006188" /><line ID="L7" From="B7" To="B8" R="0.0071140000000000005" X="0.0023510000000000002" /><line ID="L8" From="B8" To="B9" R="0.0103" X="0.0074" /><line ID="L9" From="B9" To="B10" R="0.01044" X="0.0074" /><line ID="L10" From="B10" To="B11" R="0.001966" X="0.00065" /><line ID="L11" From="B11" To="B12" R="0.003744" X="0.001238" /><line ID="L12" From="B12" To="B13" R="0.01468" X="0.01155" /><line ID="L13" From="B13" To="B14" R="0.005416" X="0.007129" /><line ID="L14" From="B14" To="B15" R="0.0059099999999999995" X="0.00526" /><line ID="L15" From="B15" To="B16" R="0.007463" X="0.00545" /><line ID="L16" From="B16" To="B17" R="0.012889999999999999" X="0.01721" /><line ID="L17" From="B17" To="B18" R="0.00732" X="0.0057399999999999994" /><line ID="L18" From="B2" To="B19" R="0.00164" X="0.001565" /><line ID="L19" From="B19" To="B20" R="0.015042" X="0.013554" /><line ID="L20" From="B20" To="B21" R="0.004095" X="0.004784" /><line ID="L21" From="B21" To="B22" R="0.007089" X="0.009373" /><line ID="L22" From="B3" To="B23" R="0.0045119999999999995" X="0.0030830000000000002" /><line ID="L23" From="B23" To="B24" R="0.00898" X="0.007090999999999999" /><line ID="L24" From="B24" To="B25" R="0.008960000000000001" X="0.007011" /><line ID="L25" From="B6" To="B26" R="0.00203" X="0.001034" /><line ID="L26" From="B26" To="B27" R="0.002842" X="0.001447" /><line ID="L27" From="B27" To="B28" R="0.010589999999999999" X="0.009337" /><line ID="L28" From="B28" To="B29" R="0.008042" X="0.007006" /><line ID="L29" From="B29" To="B30" R="0.005075" X="0.002585" /><line ID="L30" From="B30" To="B31" R="0.009744000000000001" X="0.00963" /><line ID="L31" From="B31" To="B32" R="0.003105" X="0.003619" /><line ID="L32" From="B32" To="B33" R="0.0034100000000000003" X="0.005302" /><gen ID="G1" Bus="B1"><Pmin const="0" /><Pmax const="30" /><Qmin const="-30" /><Qmax const="30" /><CostA const="0.0001" /><CostB const="0.3" /><CostC const="10" /></gen><gen ID="G2" Bus="B2"><Pmin const="0" /><Pmax const="30" /><Qmin const="-30" /><Qmax const="30" /><CostA const="0.0001" /><CostB const="0.3" /><CostC const="10" /></gen><gen ID="G3" Bus="B3"><Pmin const="0" /><Pmax const="30" /><Qmin const="-30" /><Qmax const="30" /><CostA const="0.0001" /><CostB const="0.3" /><CostC const="10" /></gen><gen ID="G6" Bus="B6"><Pmin const="0" /><Pmax const="30" /><Qmin const="-30" /><Qmax const="30" /><CostA const="0.0001" /><CostB const="0.3" /><CostC const="10" /></gen><gen ID="G8" Bus="B8"><Pmin const="0" /><Pmax const="30" /><Qmin const="-30" /><Qmax const="30" /><CostA const="0.0001" /><CostB const="0.3" /><CostC const="10" /></gen></grid>